django_cognito_jwt/__init__.py
django_cognito_jwt/backend.py
django_cognito_jwt/validator.py
django_cognito_jwt_rydra/__init__.py
django_cognito_jwt_rydra-0.0.4.dist-info/LICENSE
django_cognito_jwt_rydra-0.0.4.dist-info/WHEEL
django_cognito_jwt_rydra-0.0.4.dist-info/METADATA
django_cognito_jwt_rydra-0.0.4.dist-info/RECORD
