Metadata-Version: 2.1
Name: django-cognito-jwt-rydra
Version: 0.0.4
Summary: Django backends for AWS Cognito JWT (Forked from django-cognito-jwt with some customizations)
Home-page: https://github.com/rydra/django-cognito-jwt
License: MIT
Author: David Jiménez
Author-email: davigetto@gmail.com
Requires-Python: >=3.6,<4.0
Classifier: Environment :: Web Environment
Classifier: Framework :: Django
Classifier: Framework :: Django :: 1.11
Classifier: License :: OSI Approved :: MIT License
Classifier: Programming Language :: Python
Classifier: Programming Language :: Python :: 3
Classifier: Programming Language :: Python :: 3.6
Classifier: Programming Language :: Python :: 3.7
Classifier: Programming Language :: Python :: 3.8
Requires-Dist: cryptography (>=2.8,<3.0)
Requires-Dist: decorator (>=4.4.1,<5.0.0)
Requires-Dist: django (>=2.0,<3.0)
Requires-Dist: djangorestframework (>=3.11.0,<4.0.0)
Requires-Dist: pyjwt (>=1.7.1,<2.0.0)
Requires-Dist: redis (>=3.3.11,<4.0.0)
Requires-Dist: requests (>=2.22.0,<3.0.0)
Project-URL: Repository, https://github.com/rydra/django-cognito-jwt
